behave_cucumber_matcher/__init__.py
behave_cucumber_matcher/__version__.py
behave_cucumber_matcher/matcher.py
behave_cucumber_matcher-0.4.0.dist-info/LICENSE
behave_cucumber_matcher-0.4.0.dist-info/WHEEL
behave_cucumber_matcher-0.4.0.dist-info/METADATA
behave_cucumber_matcher-0.4.0.dist-info/RECORD
