Metadata-Version: 2.1
Name: behave-cucumber-matcher
Version: 0.4.0
Summary: Behave step matcher for Cucumber Expressions.
Author: Kieran Ryan
Requires-Python: >=3.7
Classifier: Development Status :: 4 - Beta
Classifier: Intended Audience :: Developers
Classifier: License :: OSI Approved :: MIT License
Classifier: Operating System :: OS Independent
Classifier: Programming Language :: Python :: 3 :: Only
Classifier: Programming Language :: Python :: 3.7
Classifier: Programming Language :: Python :: 3.8
Classifier: Programming Language :: Python :: 3.9
Classifier: Programming Language :: Python :: 3.10
Classifier: Programming Language :: Python :: 3.11
Classifier: Programming Language :: Python :: 3.12
Classifier: Topic :: Software Development :: Testing
Requires-Dist: behave>=1.2.6
Requires-Dist: cucumber-expressions>=10.2.0
Project-URL: Changelog, https://github.com/kieran-ryan/behave-cucumber-matcher/blob/main/CHANGELOG.md
Project-URL: Documentation, https://github.com/kieran-ryan/behave-cucumber-matcher/blob/main/README.md
Project-URL: Source, https://github.com/kieran-ryan/behave-cucumber-matcher
Project-URL: Tracker, https://github.com/kieran-ryan/behave-cucumber-matcher/issues
